netzero_metrics_reference_data/__about__.py
netzero_metrics_reference_data/__init__.py
netzero_metrics_reference_data/data/_DO-NOT-EDIT
netzero_metrics_reference_data/data/building-types.txt
netzero_metrics_reference_data/data/color-energy-end-use.csv
netzero_metrics_reference_data/data/color-fuel-type.csv
netzero_metrics_reference_data/data/datapackage.yaml
netzero_metrics_reference_data/data/energy-use-intensity.csv
netzero_metrics_reference_data/data/life-cycle-modules.csv
netzero_metrics_reference_data/data/rics-building-element-category.csv
netzero_metrics_reference_data-0.3.0.dist-info/METADATA
netzero_metrics_reference_data-0.3.0.dist-info/WHEEL
netzero_metrics_reference_data-0.3.0.dist-info/RECORD
