Metadata-Version: 2.4
Name: netzero-metrics-reference-data
Version: 0.3.0
Project-URL: Documentation, https://github.com/maxfordham/netzero-metrics-reference-data#readme
Project-URL: Issues, https://github.com/maxfordham/netzero-metrics-reference-data/issues
Project-URL: Source, https://github.com/maxfordham/netzero-metrics-reference-data
Author-email: jgunstone <j.gunstone@maxfordham.com>
Requires-Python: >=3.11
Requires-Dist: frictionless<6,>=5.18.1
